{
  "title": "Tonari no Chinatsu-chan R",
  "description": "",
  "artist": "Tukinowagamo",
  "author": "Tukinowagamo",
  "cover": "https://lolicore-subs.com/wp-content/uploads/2023/12/Tonari-no-Chinatsu-chan-R-07-Arabic-Cover-Hentai-800x1189.jpg",
  "chapters": {
    "1": {
      "title": "جارتي تشيناتسو-تشان R",
      "volume": "",
      "last_updated": "1704048101",
      "groups": {
        "Lolicore-Subs": "/proxy/api/mangadex/chapter/07547ebf-c135-442c-9378-1268e702e634"
      }
    },
    "2": {
      "title": "جارتي تشيناتسو-تشان R 02",
      "volume": "",
      "last_updated": "1704048177",
      "groups": {
        "Lolicore-Subs": "/proxy/api/mangadex/chapter/545cd4f8-878b-43ce-8e5e-99b26fd61220"
      }
    },
    "3": {
      "title": "جارتي تشيناتسو-تشان R 03",
      "volume": "",
      "last_updated": "1704048198",
      "groups": {
        "Lolicore-Subs": "/proxy/api/mangadex/chapter/48164407-5252-44d1-b1c0-b02043e2d6c1"
      }
    },
    "4": {
      "title": "جارتي تشيناتسو-تشان R 04",
      "volume": "",
      "last_updated": "1704048216",
      "groups": {
        "Lolicore-Subs": "/proxy/api/mangadex/chapter/7a468867-bdac-4238-8b55-2b51d9cb53c4"
      }
    },
    "5": {
      "title": "جارتي تشيناتسو-تشان R 05",
      "volume": "",
      "last_updated": "1704048234",
      "groups": {
        "Lolicore-Subs": "/proxy/api/mangadex/chapter/51f60737-b919-471e-b9cb-fae1a21445b0"
      }
    },
    "6": {
      "title": "جارتي تشيناتسو-تشان R 06",
      "volume": "",
      "last_updated": "1704048254",
      "groups": {
        "Lolicore-Subs": "/proxy/api/mangadex/chapter/a4e73dc1-8c4d-4f64-bad6-40635a17d08e"
      }
    },
    "7": {
      "title": "جارتي تشيناتسو-تشان R 07",
      "volume": "",
      "last_updated": "1704048268",
      "groups": {
        "Lolicore-Subs": "/proxy/api/mangadex/chapter/7b4e53f5-908a-4126-8908-6dfdd76a7a60"
      }
    }
  }
}